<locale>
	<string key="preprocess_button"><![CDATA[Preprocess]]></string>
	<string key="just_log_warning_checkbox"><![CDATA[just log warning]]></string>
	<string key="skip_convert_shape_to_graphic_checkbox"><![CDATA[skip convert shape to graphic]]></string>
	<string key="skip_convert_guided_frames_to_key_frames_checkbox"><![CDATA[skip convert guided frames to key frames]]></string>
	<string key="skip_convert_multi_layer_graphic_checkbox"><![CDATA[skip convert multi-layer graphic]]></string>
	<string key="skip_convert_multi_element_single_frame_graphic_checkbox"><![CDATA[skip convert multi-element single-frame graphic]]></string>
	<string key="export_button"><![CDATA[Export]]></string>
	<string key="skip_export_bitmap_checkbox"><![CDATA[skip export bitmap]]></string>
	<string key="skip_export_filter_checkbox"><![CDATA[skip export filter]]></string>
	<string key="pack_image_sheet_checkbox"><![CDATA[pack image sheet]]></string>
</locale>
